[
  {"id": 5, "name": "3Sixteen", "total_mentions": 7},
  {"id": 5, "name": "3sixteen", "total_mentions": 4},
  {"id": 7, "name": "5.11", "total_mentions": 13},
  {"id": 7, "name": "5.11 Tactical", "total_mentions": 15},
  {"id": 13, "name": "7 For All Mankind", "total_mentions": 5},
  {"id": 13, "name": "7 for All Mankind", "total_mentions": 3},
  {"id": 15, "name": "A New Day", "total_mentions": 2},
  {"id": 18, "name": "Abercrombie", "total_mentions": 21},
  {"id": 22, "name": "Acne", "total_mentions": 2},
  {"id": 31, "name": "AG", "total_mentions": 3},
  {"id": 31, "name": "AG Jeans", "total_mentions": 4},
  {"id": 33, "name": "Agolde", "total_mentions": 10},
  {"id": 36, "name": "Akro-Mils", "total_mentions": 2},
  {"id": 38, "name": "Alden", "total_mentions": 3},
  {"id": 40, "name": "All American Clothing", "total_mentions": 2},
  {"id": 43, "name": "All-Clad", "total_mentions": 3},
  {"id": 45, "name": "Allen Edmonds", "total_mentions": 7},
  {"id": 46, "name": "Allsaints", "total_mentions": 2},
  {"id": 53, "name": "American Eagle", "total_mentions": 71},
  {"id": 54, "name": "American Giant", "total_mentions": 6},
  {"id": 55, "name": "American Tall", "total_mentions": 2},
  {"id": 56, "name": "And Sons", "total_mentions": 2},
  {"id": 58, "name": "Ann Taylor", "total_mentions": 4},
  {"id": 59, "name": "APC", "total_mentions": 8},
  {"id": 60, "name": "Arborwear", "total_mentions": 4},
  {"id": 61, "name": "Arc'teryx", "total_mentions": 3},
  {"id": 61, "name": "Arcteryx", "total_mentions": 4},
  {"id": 64, "name": "Ariat", "total_mentions": 51},
  {"id": 65, "name": "Ariel Vila", "total_mentions": 3},
  {"id": 66, "name": "Aritsugu", "total_mentions": 3},
  {"id": 67, "name": "Arizona", "total_mentions": 3},
  {"id": 67, "name": "Arizona Jeans", "total_mentions": 2},
  {"id": 71, "name": "ASICS", "total_mentions": 2},
  {"id": 72, "name": "Asket", "total_mentions": 4},
  {"id": 74, "name": "Asolo", "total_mentions": 6},
  {"id": 76, "name": "Asphalte", "total_mentions": 4},
  {"id": 79, "name": "ATG", "total_mentions": 2},
  {"id": 80, "name": "Athleta", "total_mentions": 9},
  {"id": 81, "name": "Atlas 46", "total_mentions": 4},
  {"id": 85, "name": "AYR", "total_mentions": 4},
  {"id": 89, "name": "Banana Republic", "total_mentions": 25},
  {"id": 91, "name": "Barbell", "total_mentions": 6},
  {"id": 91, "name": "Barbell Apparel", "total_mentions": 2},
  {"id": 93, "name": "Barbour", "total_mentions": 10},
  {"id": 100, "name": "Bear Bottoms", "total_mentions": 2},
  {"id": 106, "name": "Benelli", "total_mentions": 2},
  {"id": 107, "name": "Benetton", "total_mentions": 2},
  {"id": 109, "name": "Beretta", "total_mentions": 2},
  {"id": 110, "name": "Bernina", "total_mentions": 4},
  {"id": 112, "name": "Bic Camera", "total_mentions": 2},
  {"id": 115, "name": "Bills Khakis", "total_mentions": 2},
  {"id": 117, "name": "Birkenstock", "total_mentions": 9},
  {"id": 117, "name": "Birkenstocks", "total_mentions": 28},
  {"id": 121, "name": "Black & Decker", "total_mentions": 8},
  {"id": 121, "name": "Black and Decker", "total_mentions": 10},
  {"id": 123, "name": "Black Horse Lane Ateliers", "total_mentions": 2},
  {"id": 126, "name": "Blaklader", "total_mentions": 3},
  {"id": 129, "name": "Blue Mountain", "total_mentions": 3},
  {"id": 131, "name": "Bluffworks", "total_mentions": 2},
  {"id": 132, "name": "Blundstone", "total_mentions": 6},
  {"id": 135, "name": "Boden", "total_mentions": 2},
  {"id": 136, "name": "Bogs", "total_mentions": 2},
  {"id": 138, "name": "Bonobos", "total_mentions": 8},
  {"id": 139, "name": "Book Off", "total_mentions": 3},
  {"id": 141, "name": "Born", "total_mentions": 4},
  {"id": 144, "name": "Bostitch", "total_mentions": 2},
  {"id": 145, "name": "Bradley Cooper", "total_mentions": 2},
  {"id": 146, "name": "Bragg's", "total_mentions": 2},
  {"id": 149, "name": "Brave Star", "total_mentions": 24},
  {"id": 149, "name": "Brave Star Selvage", "total_mentions": 3},
  {"id": 149, "name": "Brave Star Selvege", "total_mentions": 3},
  {"id": 152, "name": "Bravestar", "total_mentions": 19},
  {"id": 152, "name": "Bravestars", "total_mentions": 2},
  {"id": 155, "name": "Brax", "total_mentions": 3},
  {"id": 157, "name": "Brooks", "total_mentions": 3},
  {"id": 157, "name": "Brooks Brothers", "total_mentions": 5},
  {"id": 160, "name": "Brother", "total_mentions": 4},
  {"id": 161, "name": "BruMate", "total_mentions": 4},
  {"id": 162, "name": "Bubba", "total_mentions": 3},
  {"id": 164, "name": "Buckle", "total_mentions": 2},
  {"id": 164, "name": "Buckle Guy", "total_mentions": 3},
  {"id": 167, "name": "Buffalo", "total_mentions": 5},
  {"id": 169, "name": "Bulletprufe", "total_mentions": 2},
  {"id": 172, "name": "Burberry", "total_mentions": 2},
  {"id": 174, "name": "Burlington", "total_mentions": 3},
  {"id": 177, "name": "Cabela's", "total_mentions": 3},
  {"id": 177, "name": "Cabelas", "total_mentions": 5},
  {"id": 179, "name": "Calvin Klein", "total_mentions": 5},
  {"id": 180, "name": "CamelBak", "total_mentions": 7},
  {"id": 181, "name": "Canada Goose", "total_mentions": 2},
  {"id": 182, "name": "Canadian Tire", "total_mentions": 2},
  {"id": 183, "name": "Canadian Tuxedo", "total_mentions": 2},
  {"id": 184, "name": "Candiani", "total_mentions": 3},
  {"id": 185, "name": "Captain Morgan", "total_mentions": 3},
  {"id": 186, "name": "Carhartt", "total_mentions": 366},
  {"id": 189, "name": "Casio", "total_mentions": 3},
  {"id": 190, "name": "Castelli", "total_mentions": 2},
  {"id": 196, "name": "Chacos", "total_mentions": 4},
  {"id": 197, "name": "Chanel", "total_mentions": 8},
  {"id": 202, "name": "Chippewa", "total_mentions": 2},
  {"id": 204, "name": "Chrome Industries", "total_mentions": 4},
  {"id": 206, "name": "Cinch", "total_mentions": 16},
  {"id": 207, "name": "Citizen", "total_mentions": 3},
  {"id": 208, "name": "Citizens of Humanity", "total_mentions": 8},
  {"id": 211, "name": "Clarks", "total_mentions": 5},
  {"id": 217, "name": "Coalatree", "total_mentions": 2},
  {"id": 219, "name": "Coleman", "total_mentions": 4},
  {"id": 222, "name": "Columbia", "total_mentions": 23},
  {"id": 227, "name": "Cone Mills", "total_mentions": 5},
  {"id": 228, "name": "Contigo", "total_mentions": 7},
  {"id": 229, "name": "Converse", "total_mentions": 6},
  {"id": 230, "name": "Corelle", "total_mentions": 3},
  {"id": 232, "name": "Cornwell", "total_mentions": 2},
  {"id": 234, "name": "Costco", "total_mentions": 52},
  {"id": 235, "name": "Costco Kirkland", "total_mentions": 13},
  {"id": 237, "name": "CQR", "total_mentions": 4},
  {"id": 238, "name": "Craftsman", "total_mentions": 76},
  {"id": 240, "name": "Cuisinart", "total_mentions": 3},
  {"id": 245, "name": "Danner", "total_mentions": 13},
  {"id": 246, "name": "Dansko", "total_mentions": 5},
  {"id": 247, "name": "Darn Tough", "total_mentions": 17},
  {"id": 251, "name": "Dearborn Denim", "total_mentions": 29},
  {"id": 255, "name": "Dehen 1920", "total_mentions": 2},
  {"id": 258, "name": "Denham", "total_mentions": 2},
  {"id": 259, "name": "Denizen", "total_mentions": 4},
  {"id": 260, "name": "Denman", "total_mentions": 3},
  {"id": 261, "name": "Detroit Denim Company", "total_mentions": 2},
  {"id": 263, "name": "Devil-Dog", "total_mentions": 2},
  {"id": 264, "name": "DeWalt", "total_mentions": 5},
  {"id": 265, "name": "Diamond Gusset", "total_mentions": 34},
  {"id": 266, "name": "Dickies", "total_mentions": 105},
  {"id": 267, "name": "Diesel", "total_mentions": 18},
  {"id": 268, "name": "Dillards", "total_mentions": 3},
  {"id": 270, "name": "Doc Marten", "total_mentions": 8},
  {"id": 270, "name": "Doc Martens", "total_mentions": 29},
  {"id": 272, "name": "Dockers", "total_mentions": 2},
  {"id": 273, "name": "Dolce & Gabbana", "total_mentions": 2},
  {"id": 274, "name": "DomesticDomestic", "total_mentions": 2},
  {"id": 276, "name": "Don Quijote", "total_mentions": 3},
  {"id": 270, "name": "Dr. Martens", "total_mentions": 2},
  {"id": 280, "name": "Dremel", "total_mentions": 3},
  {"id": 281, "name": "Du/Er", "total_mentions": 2},
  {"id": 283, "name": "Duer", "total_mentions": 37},
  {"id": 283, "name": "DUER", "total_mentions": 6},
  {"id": 286, "name": "Duluth", "total_mentions": 79},
  {"id": 286, "name": "Duluth Trading", "total_mentions": 55},
  {"id": 286, "name": "Duluth Trading Co", "total_mentions": 13},
  {"id": 286, "name": "Duluth Trading Co.", "total_mentions": 7},
  {"id": 296, "name": "Duluth Trading Company", "total_mentions": 199},
  {"id": 296, "name": "Ecoalf", "total_mentions": 3},
  {"id": 297, "name": "Eddie Bauer", "total_mentions": 41},
  {"id": 298, "name": "Edwin", "total_mentions": 23},
  {"id": 299, "name": "Eileen Fisher", "total_mentions": 9},
  {"id": 304, "name": "Engineered Garments", "total_mentions": 2},
  {"id": 307, "name": "Esprit", "total_mentions": 2},
  {"id": 308, "name": "Everlane", "total_mentions": 29},
  {"id": 309, "name": "Evisu", "total_mentions": 4},
  {"id": 311, "name": "Express", "total_mentions": 4},
  {"id": 314, "name": "Family Mart", "total_mentions": 2},
  {"id": 315, "name": "Fat Max", "total_mentions": 22},
  {"id": 318, "name": "Fender", "total_mentions": 7},
  {"id": 320, "name": "Filson", "total_mentions": 38},
  {"id": 324, "name": "Fjallraven", "total_mentions": 44},
  {"id": 324, "name": "FJALLRAVEN", "total_mentions": 2},
  {"id": 324, "name": "Fj\u00e4llr\u00e4ven", "total_mentions": 3},
  {"id": 328, "name": "Flint and Tinder", "total_mentions": 3},
  {"id": 329, "name": "Florsheim", "total_mentions": 3},
  {"id": 332, "name": "Forever 21", "total_mentions": 4},
  {"id": 335, "name": "Fox Creek Leather", "total_mentions": 10},
  {"id": 337, "name": "Freenote Cloth", "total_mentions": 4},
  {"id": 341, "name": "Frye", "total_mentions": 6},
  {"id": 342, "name": "Full Count", "total_mentions": 5},
  {"id": 344, "name": "FX Networks", "total_mentions": 2},
  {"id": 345, "name": "G-Star", "total_mentions": 7},
  {"id": 346, "name": "Gap", "total_mentions": 69},
  {"id": 346, "name": "GAP", "total_mentions": 7},
  {"id": 351, "name": "George", "total_mentions": 3},
  {"id": 352, "name": "Gerber", "total_mentions": 3},
  {"id": 356, "name": "Gloria Vanderbilt", "total_mentions": 2},
  {"id": 360, "name": "Good American", "total_mentions": 3},
  {"id": 361, "name": "Goodfellow", "total_mentions": 4},
  {"id": 364, "name": "Goodwill", "total_mentions": 6},
  {"id": 365, "name": "Goodyear", "total_mentions": 2},
  {"id": 375, "name": "Green Bell", "total_mentions": 6},
  {"id": 376, "name": "GRIP6", "total_mentions": 2},
  {"id": 377, "name": "Griswold", "total_mentions": 2},
  {"id": 381, "name": "Gusset", "total_mentions": 2},
  {"id": 382, "name": "Gustin", "total_mentions": 75},
  {"id": 384, "name": "Hanes", "total_mentions": 5},
  {"id": 385, "name": "Hank's", "total_mentions": 4},
  {"id": 385, "name": "Hanks", "total_mentions": 5},
  {"id": 389, "name": "Harbor Freight", "total_mentions": 7},
  {"id": 390, "name": "Harley Davidson", "total_mentions": 2},
  {"id": 392, "name": "Hartford Denim Company", "total_mentions": 5},
  {"id": 393, "name": "Hartmann", "total_mentions": 2},
  {"id": 404, "name": "Hiroshi Kato", "total_mentions": 6},
  {"id": 405, "name": "Hiut", "total_mentions": 3},
  {"id": 405, "name": "Hiut Denim", "total_mentions": 2},
  {"id": 410, "name": "Hollister", "total_mentions": 3},
  {"id": 414, "name": "Howies", "total_mentions": 2},
  {"id": 417, "name": "Hudson", "total_mentions": 10},
  {"id": 419, "name": "Huit", "total_mentions": 4},
  {"id": 420, "name": "Hunter", "total_mentions": 2},
  {"id": 421, "name": "Husky", "total_mentions": 3},
  {"id": 428, "name": "Imogene + Willie", "total_mentions": 4},
  {"id": 428, "name": "Imogene and Willie", "total_mentions": 3},
  {"id": 430, "name": "Indigofera", "total_mentions": 2},
  {"id": 432, "name": "Iron Flask", "total_mentions": 4},
  {"id": 433, "name": "Iron Heart", "total_mentions": 113},
  {"id": 433, "name": "Iron Hearts", "total_mentions": 2},
  {"id": 435, "name": "Iron Rangers", "total_mentions": 15},
  {"id": 438, "name": "Izod", "total_mentions": 3},
  {"id": 440, "name": "J Crew", "total_mentions": 4},
  {"id": 440, "name": "J.Crew", "total_mentions": 2},
  {"id": 443, "name": "Jack & Jones", "total_mentions": 2},
  {"id": 443, "name": "Jack and Jones", "total_mentions": 3},
  {"id": 446, "name": "Janome", "total_mentions": 4},
  {"id": 447, "name": "Japan Blue", "total_mentions": 5},
  {"id": 447, "name": "Japan Blue Jeans", "total_mentions": 3},
  {"id": 449, "name": "Jason", "total_mentions": 2},
  {"id": 451, "name": "Jeans West", "total_mentions": 4},
  {"id": 456, "name": "JNCO", "total_mentions": 2},
  {"id": 461, "name": "Joe's Jeans", "total_mentions": 5},
  {"id": 463, "name": "John Deere", "total_mentions": 5},
  {"id": 473, "name": "Kato", "total_mentions": 3},
  {"id": 477, "name": "Kenmore", "total_mentions": 13},
  {"id": 478, "name": "Kershaw", "total_mentions": 4},
  {"id": 479, "name": "Key", "total_mentions": 2},
  {"id": 479, "name": "Key Apparel", "total_mentions": 3},
  {"id": 485, "name": "Kirkland", "total_mentions": 27},
  {"id": 493, "name": "Kobalt", "total_mentions": 5},
  {"id": 500, "name": "Kuhl", "total_mentions": 15},
  {"id": 500, "name": "KUHL", "total_mentions": 4},
  {"id": 502, "name": "Kuiu", "total_mentions": 2},
  {"id": 503, "name": "Kut from the Kloth", "total_mentions": 2},
  {"id": 500, "name": "K\u00fchl", "total_mentions": 5},
  {"id": 506, "name": "L L Bean", "total_mentions": 2},
  {"id": 506, "name": "L.L. Bean", "total_mentions": 38},
  {"id": 513, "name": "Land's End", "total_mentions": 8},
  {"id": 513, "name": "Lands End", "total_mentions": 11},
  {"id": 513, "name": "Lands' End", "total_mentions": 5},
  {"id": 516, "name": "Langlitz Leather", "total_mentions": 3},
  {"id": 517, "name": "Lansky", "total_mentions": 2},
  {"id": 519, "name": "LazyBoy", "total_mentions": 8},
  {"id": 521, "name": "Le Creuset", "total_mentions": 5},
  {"id": 522, "name": "Leatherman", "total_mentions": 4},
  {"id": 524, "name": "Lee", "total_mentions": 165},
  {"id": 525, "name": "Left Field", "total_mentions": 4},
  {"id": 528, "name": "Leftfield NYC", "total_mentions": 2},
  {"id": 1, "name": "Levi", "total_mentions": 5},
  {"id": 1, "name": "Levi's", "total_mentions": 2009},
  {"id": 1, "name": "Levi's Vintage Clothing", "total_mentions": 3},
  {"id": 1, "name": "Levis", "total_mentions": 57},
  {"id": 1, "name": "Levis Made and Crafted", "total_mentions": 2},
  {"id": 539, "name": "Lil Joe's Leather", "total_mentions": 2},
  {"id": 543, "name": "Livid", "total_mentions": 4},
  {"id": 506, "name": "LL Bean", "total_mentions": 86},
  {"id": 546, "name": "Lodge", "total_mentions": 19},
  {"id": 547, "name": "Loft", "total_mentions": 2},
  {"id": 552, "name": "Lucky", "total_mentions": 34},
  {"id": 552, "name": "Lucky Brand", "total_mentions": 68},
  {"id": 552, "name": "Lucky Jeans", "total_mentions": 5},
  {"id": 555, "name": "Lufkin", "total_mentions": 4},
  {"id": 556, "name": "Lululemon", "total_mentions": 30},
  {"id": 557, "name": "Lupicia", "total_mentions": 2},
  {"id": 558, "name": "LVC", "total_mentions": 8},
  {"id": 559, "name": "M&S", "total_mentions": 2},
  {"id": 564, "name": "Made and Crafted", "total_mentions": 10},
  {"id": 565, "name": "Madewell", "total_mentions": 63},
  {"id": 569, "name": "Marine Layer", "total_mentions": 2},
  {"id": 577, "name": "Matco", "total_mentions": 3},
  {"id": 579, "name": "Mavi", "total_mentions": 5},
  {"id": 582, "name": "MEC", "total_mentions": 12},
  {"id": 588, "name": "Merona", "total_mentions": 3},
  {"id": 589, "name": "Merrell", "total_mentions": 14},
  {"id": 591, "name": "Merz b. Schwanen", "total_mentions": 2},
  {"id": 597, "name": "Milwaukee", "total_mentions": 11},
  {"id": 598, "name": "Ministry of Supply", "total_mentions": 2},
  {"id": 602, "name": "Mission Workshop", "total_mentions": 3},
  {"id": 605, "name": "MJ Bale", "total_mentions": 2},
  {"id": 606, "name": "Momotaro", "total_mentions": 51},
  {"id": 607, "name": "Montbell", "total_mentions": 2},
  {"id": 608, "name": "Moose Knuckles", "total_mentions": 2},
  {"id": 609, "name": "Mossberg", "total_mentions": 2},
  {"id": 612, "name": "Mountain Hardwear", "total_mentions": 3},
  {"id": 614, "name": "Mountain Khaki", "total_mentions": 5},
  {"id": 614, "name": "Mountain Khakis", "total_mentions": 2},
  {"id": 616, "name": "MSPC Masterpiece", "total_mentions": 2},
  {"id": 618, "name": "MUD Jeans", "total_mentions": 3},
  {"id": 618, "name": "Mud Jeans", "total_mentions": 2},
  {"id": 620, "name": "Mugsy", "total_mentions": 2},
  {"id": 621, "name": "Muji", "total_mentions": 4},
  {"id": 624, "name": "M\u00fchle", "total_mentions": 2},
  {"id": 625, "name": "Naked & Famous", "total_mentions": 57},
  {"id": 625, "name": "Naked and Famous", "total_mentions": 93},
  {"id": 635, "name": "New Balance", "total_mentions": 4},
  {"id": 638, "name": "Nike", "total_mentions": 12},
  {"id": 645, "name": "North Face", "total_mentions": 52},
  {"id": 647, "name": "Nudie", "total_mentions": 83},
  {"id": 647, "name": "Nudie Jeans", "total_mentions": 35},
  {"id": 647, "name": "Nudies", "total_mentions": 10},
  {"id": 651, "name": "Occidental Leather", "total_mentions": 2},
  {"id": 656, "name": "Old Navy", "total_mentions": 71},
  {"id": 660, "name": "Oni", "total_mentions": 30},
  {"id": 662, "name": "Onitsuka Tiger", "total_mentions": 2},
  {"id": 668, "name": "Origami Dojo", "total_mentions": 2},
  {"id": 669, "name": "Origin", "total_mentions": 32},
  {"id": 675, "name": "Orion", "total_mentions": 13},
  {"id": 678, "name": "Orslow", "total_mentions": 6},
  {"id": 682, "name": "Oster", "total_mentions": 2},
  {"id": 687, "name": "Outlier", "total_mentions": 18},
  {"id": 688, "name": "Owala", "total_mentions": 38},
  {"id": 689, "name": "Oxyclean", "total_mentions": 6},
  {"id": 691, "name": "Ozark Trail", "total_mentions": 6},
  {"id": 693, "name": "Paige", "total_mentions": 15},
  {"id": 695, "name": "Panera", "total_mentions": 4},
  {"id": 697, "name": "Patagonia", "total_mentions": 89},
  {"id": 699, "name": "Pearl Izumi", "total_mentions": 2},
  {"id": 701, "name": "PeDaled", "total_mentions": 2},
  {"id": 702, "name": "Pendleton", "total_mentions": 19},
  {"id": 704, "name": "Pepe", "total_mentions": 4},
  {"id": 709, "name": "Pike Brothers", "total_mentions": 2},
  {"id": 710, "name": "Pilot", "total_mentions": 4},
  {"id": 715, "name": "Pointer", "total_mentions": 3},
  {"id": 716, "name": "Pointer Brand", "total_mentions": 2},
  {"id": 717, "name": "Polo Ralph Lauren", "total_mentions": 2},
  {"id": 719, "name": "Porter Cable", "total_mentions": 2},
  {"id": 723, "name": "Prana", "total_mentions": 21},
  {"id": 727, "name": "Prison Blues", "total_mentions": 25},
  {"id": 729, "name": "Project Farm", "total_mentions": 5},
  {"id": 731, "name": "Proof NY", "total_mentions": 4},
  {"id": 734, "name": "Pull & Bear", "total_mentions": 4},
  {"id": 736, "name": "Puma", "total_mentions": 3},
  {"id": 737, "name": "Pure Blue Japan", "total_mentions": 20},
  {"id": 738, "name": "Purist", "total_mentions": 4},
  {"id": 739, "name": "Pyrex", "total_mentions": 62},
  {"id": 740, "name": "Q-tips", "total_mentions": 2},
  {"id": 741, "name": "Quince", "total_mentions": 3},
  {"id": 742, "name": "Quiznos", "total_mentions": 6},
  {"id": 743, "name": "r/rawdenim", "total_mentions": 4},
  {"id": 745, "name": "Rag and Bone", "total_mentions": 2},
  {"id": 747, "name": "Railcar", "total_mentions": 8},
  {"id": 749, "name": "Raleigh", "total_mentions": 12},
  {"id": 750, "name": "Raleigh Denim", "total_mentions": 12},
  {"id": 751, "name": "Raleigh Denim Workshop", "total_mentions": 4},
  {"id": 752, "name": "Ralph Lauren", "total_mentions": 10},
  {"id": 755, "name": "Rapha", "total_mentions": 2},
  {"id": 759, "name": "Red Head", "total_mentions": 2},
  {"id": 760, "name": "Red Kap", "total_mentions": 3},
  {"id": 762, "name": "Red Wing", "total_mentions": 70},
  {"id": 764, "name": "Reddit", "total_mentions": 3},
  {"id": 766, "name": "Redhead", "total_mentions": 2},
  {"id": 768, "name": "Redwing", "total_mentions": 3},
  {"id": 769, "name": "Reebok", "total_mentions": 2},
  {"id": 771, "name": "REI", "total_mentions": 6},
  {"id": 772, "name": "REI Co-op", "total_mentions": 4},
  {"id": 773, "name": "RemindMeBot", "total_mentions": 3},
  {"id": 774, "name": "Remington", "total_mentions": 5},
  {"id": 775, "name": "Replay", "total_mentions": 2},
  {"id": 778, "name": "Revolvr", "total_mentions": 2},
  {"id": 779, "name": "Revtown", "total_mentions": 12},
  {"id": 782, "name": "Riggs", "total_mentions": 3},
  {"id": 785, "name": "RM Williams", "total_mentions": 2},
  {"id": 790, "name": "Rockstar", "total_mentions": 2},
  {"id": 791, "name": "Rogue Territory", "total_mentions": 4},
  {"id": 793, "name": "Rolex", "total_mentions": 7},
  {"id": 794, "name": "Roots", "total_mentions": 2},
  {"id": 796, "name": "Ross", "total_mentions": 24},
  {"id": 797, "name": "Round House", "total_mentions": 7},
  {"id": 798, "name": "Roundhouse", "total_mentions": 16},
  {"id": 800, "name": "RRL", "total_mentions": 15},
  {"id": 801, "name": "RSQ", "total_mentions": 4},
  {"id": 803, "name": "RTIC", "total_mentions": 15},
  {"id": 804, "name": "Rubbermaid", "total_mentions": 7},
  {"id": 805, "name": "Rudy Jude", "total_mentions": 5},
  {"id": 807, "name": "Rural King", "total_mentions": 2},
  {"id": 808, "name": "Rustic Dime", "total_mentions": 3},
  {"id": 809, "name": "Rustler", "total_mentions": 24},
  {"id": 810, "name": "Rustlers", "total_mentions": 3},
  {"id": 812, "name": "Ryobi", "total_mentions": 2},
  {"id": 818, "name": "Salomon", "total_mentions": 5},
  {"id": 819, "name": "Salsa", "total_mentions": 2},
  {"id": 820, "name": "Sam's", "total_mentions": 3},
  {"id": 821, "name": "Sam's Club", "total_mentions": 2},
  {"id": 822, "name": "Samsung", "total_mentions": 7},
  {"id": 823, "name": "Samurai", "total_mentions": 38},
  {"id": 825, "name": "Satchel and Page", "total_mentions": 2},
  {"id": 826, "name": "Schott", "total_mentions": 5},
  {"id": 829, "name": "Scotch and Soda", "total_mentions": 2},
  {"id": 832, "name": "Sebo", "total_mentions": 2},
  {"id": 833, "name": "Seiko", "total_mentions": 12},
  {"id": 835, "name": "Self Edge", "total_mentions": 4},
  {"id": 836, "name": "Sene", "total_mentions": 2},
  {"id": 837, "name": "Serious Eats", "total_mentions": 3},
  {"id": 838, "name": "Seth Rogen", "total_mentions": 2},
  {"id": 839, "name": "Seven", "total_mentions": 3},
  {"id": 840, "name": "Seven For All Mankind", "total_mentions": 2},
  {"id": 843, "name": "Shein", "total_mentions": 2},
  {"id": 847, "name": "Shockoe Atelier", "total_mentions": 6},
  {"id": 848, "name": "Showers Pass", "total_mentions": 4},
  {"id": 850, "name": "Sigg", "total_mentions": 5},
  {"id": 851, "name": "Silver", "total_mentions": 9},
  {"id": 853, "name": "Singer", "total_mentions": 22},
  {"id": 854, "name": "Smartwool", "total_mentions": 10},
  {"id": 855, "name": "Snap-on", "total_mentions": 11},
  {"id": 856, "name": "Snap-On", "total_mentions": 2},
  {"id": 857, "name": "Snapper", "total_mentions": 2},
  {"id": 859, "name": "Snow Peak", "total_mentions": 2},
  {"id": 862, "name": "Solovair", "total_mentions": 2},
  {"id": 865, "name": "Sons of Anarchy", "total_mentions": 3},
  {"id": 866, "name": "Sony", "total_mentions": 4},
  {"id": 867, "name": "Sorel", "total_mentions": 30},
  {"id": 868, "name": "Sorels", "total_mentions": 8},
  {"id": 870, "name": "Speed Queen", "total_mentions": 2},
  {"id": 877, "name": "Stanley", "total_mentions": 90},
  {"id": 878, "name": "Starbucks", "total_mentions": 2},
  {"id": 881, "name": "Staub", "total_mentions": 3},
  {"id": 886, "name": "Stormrider", "total_mentions": 3},
  {"id": 888, "name": "Strike Gold", "total_mentions": 5},
  {"id": 889, "name": "Stronghold", "total_mentions": 4},
  {"id": 890, "name": "Studio Artisan", "total_mentions": 3},
  {"id": 891, "name": "Studio d'Artisan", "total_mentions": 2},
  {"id": 894, "name": "Studio Dartisan", "total_mentions": 6},
  {"id": 895, "name": "Sugar Cane", "total_mentions": 7},
  {"id": 896, "name": "Sugar Cane & Co", "total_mentions": 3},
  {"id": 899, "name": "Supreme", "total_mentions": 2},
  {"id": 902, "name": "Swell", "total_mentions": 2},
  {"id": 903, "name": "Swrve", "total_mentions": 10},
  {"id": 905, "name": "Tajima", "total_mentions": 2},
  {"id": 906, "name": "Takeya", "total_mentions": 6},
  {"id": 909, "name": "Tandy Leather", "total_mentions": 4},
  {"id": 911, "name": "Tanuki", "total_mentions": 3},
  {"id": 912, "name": "Target", "total_mentions": 20},
  {"id": 915, "name": "Tate and Yoko", "total_mentions": 3},
  {"id": 917, "name": "Taylor Stitch", "total_mentions": 10},
  {"id": 918, "name": "TCB", "total_mentions": 6},
  {"id": 919, "name": "Teddy Jeans", "total_mentions": 2},
  {"id": 920, "name": "Tekton", "total_mentions": 5},
  {"id": 921, "name": "Tellason", "total_mentions": 28},
  {"id": 923, "name": "Temu", "total_mentions": 3},
  {"id": 924, "name": "Tesco", "total_mentions": 2},
  {"id": 926, "name": "Texas Jeans", "total_mentions": 3},
  {"id": 927, "name": "The Belt Man", "total_mentions": 2},
  {"id": 928, "name": "The Beltman", "total_mentions": 2},
  {"id": 929, "name": "The Flat Head", "total_mentions": 2},
  {"id": 930, "name": "The Gap", "total_mentions": 3},
  {"id": 932, "name": "The North Face", "total_mentions": 2},
  {"id": 934, "name": "Thermoflask", "total_mentions": 5},
  {"id": 938, "name": "Thursday Boots", "total_mentions": 5},
  {"id": 939, "name": "Thyssens", "total_mentions": 2},
  {"id": 940, "name": "Tilley", "total_mentions": 3},
  {"id": 941, "name": "Timberland", "total_mentions": 27},
  {"id": 942, "name": "TimBuk2", "total_mentions": 2},
  {"id": 944, "name": "TJ Maxx", "total_mentions": 3},
  {"id": 946, "name": "Todd Snyder", "total_mentions": 3},
  {"id": 947, "name": "Tokyu Hands", "total_mentions": 2},
  {"id": 950, "name": "Tombow", "total_mentions": 2},
  {"id": 953, "name": "Tommy Hilfiger", "total_mentions": 5},
  {"id": 955, "name": "Tonka", "total_mentions": 2},
  {"id": 956, "name": "Topo Designs", "total_mentions": 2},
  {"id": 957, "name": "Topshop", "total_mentions": 2},
  {"id": 958, "name": "Toter", "total_mentions": 2},
  {"id": 959, "name": "Toyota", "total_mentions": 19},
  {"id": 960, "name": "Tractor Supply", "total_mentions": 3},
  {"id": 962, "name": "Tramontina", "total_mentions": 10},
  {"id": 965, "name": "Triumph", "total_mentions": 2},
  {"id": 966, "name": "Tru-Spec", "total_mentions": 2},
  {"id": 967, "name": "True Religion", "total_mentions": 2},
  {"id": 968, "name": "Truewerk", "total_mentions": 2},
  {"id": 969, "name": "Truwerk", "total_mentions": 2},
  {"id": 971, "name": "Tumi", "total_mentions": 3},
  {"id": 972, "name": "Tunnel Vision", "total_mentions": 2},
  {"id": 974, "name": "Unbranded", "total_mentions": 106},
  {"id": 975, "name": "Unbranded Brand", "total_mentions": 6},
  {"id": 978, "name": "Union Made Brand", "total_mentions": 2},
  {"id": 979, "name": "Uniqlo", "total_mentions": 140},
  {"id": 982, "name": "Urban Heritage", "total_mentions": 2},
  {"id": 983, "name": "Urban Outfitters", "total_mentions": 4},
  {"id": 985, "name": "Urban Star", "total_mentions": 5},
  {"id": 987, "name": "Vanson", "total_mentions": 2},
  {"id": 988, "name": "Varusteleka", "total_mentions": 5},
  {"id": 989, "name": "Varustelekas", "total_mentions": 2},
  {"id": 992, "name": "Vibram", "total_mentions": 3},
  {"id": 997, "name": "Volcom", "total_mentions": 4},
  {"id": 999, "name": "Volvo", "total_mentions": 2},
  {"id": 1001, "name": "Wahl", "total_mentions": 10},
  {"id": 1004, "name": "Walmart", "total_mentions": 94},
  {"id": 1006, "name": "WD-40", "total_mentions": 3},
  {"id": 1007, "name": "Weatherproof", "total_mentions": 3},
  {"id": 1008, "name": "Weber", "total_mentions": 4},
  {"id": 1009, "name": "Webstaurant", "total_mentions": 2},
  {"id": 1010, "name": "Weekday", "total_mentions": 3},
  {"id": 1015, "name": "WiesMade", "total_mentions": 2},
  {"id": 1016, "name": "Wild Ass", "total_mentions": 4},
  {"id": 1018, "name": "Wilson's Leather", "total_mentions": 2},
  {"id": 1021, "name": "Wolverine", "total_mentions": 8},
  {"id": 1022, "name": "Woolrich", "total_mentions": 2},
  {"id": 1023, "name": "Wrangler", "total_mentions": 488},
  {"id": 1025, "name": "Wrangler Riggs", "total_mentions": 5},
  {"id": 1026, "name": "Wranglers", "total_mentions": 12},
  {"id": 1028, "name": "Yeti", "total_mentions": 57},
  {"id": 1029, "name": "Yodobashi", "total_mentions": 2},
  {"id": 1030, "name": "Yoshida Porter", "total_mentions": 2},
  {"id": 1032, "name": "Yukon Outfitters", "total_mentions": 3},
  {"id": 1034, "name": "Zanerobe", "total_mentions": 2},
  {"id": 1035, "name": "Zara", "total_mentions": 10},
  {"id": 1037, "name": "Zojirushi", "total_mentions": 17}
]
